{"id":"JSFQPE47VPLBA","name":"原创作品：游戏《保卫萝卜》宣传图","size":177246,"ext":"jpg","tags":[],"folders":["JRCWUUXEKZCKJ"],"isDeleted":false,"url":"http://www.zcool.com.cn/work/ZMzg0MTkzMg==.html","annotation":"","modificationTime":1550820859576,"noThumbnail":true,"width":900,"height":561,"lastModified":1550820968927,"palettes":[{"color":[203,189,80],"ratio":45.94969300851654},{"color":[49,141,98],"ratio":21.21212121212121},{"color":[206,213,221],"ratio":18.75618934442464},{"color":[163,62,34],"ratio":3.4066151713210537},{"color":[105,175,38],"ratio":10.675381263616558}]}