{"annotation":"","ext":"jpg","folders":["JRFVY8QUPQKXA","JRFVWA3SXEP4Q"],"height":1323,"id":"JRFVYT4ZHQINT","isDeleted":false,"lastModified":1567270663701,"modificationTime":1548652925681,"name":"312796943","noThumbnail":true,"palettes":[{"color":[179,174,164],"ratio":64.28151507516587},{"color":[47,49,44],"ratio":20.441756949693456},{"color":[103,90,60],"ratio":5.366591080876796},{"color":[102,56,48],"ratio":3.804484756865709},{"color":[102,102,90],"ratio":6.1056521373981685}],"size":339732,"tags":["中国风"],"url":"","width":900}