{"annotation":"","ext":"jpg","folders":["JRFUWIUFUQH7N","JZZMM5FHSJUV9"],"height":901,"id":"JRFUXGOXWTC2J","isDeleted":false,"lastModified":1567271341054,"modificationTime":1548651183267,"name":"875692119","noThumbnail":true,"palettes":[{"$$hashKey":"object:16993","color":[60,54,48],"ratio":77.94756313334406},{"$$hashKey":"object:16994","color":[239,233,229],"ratio":16.326202348399548},{"$$hashKey":"object:16995","color":[140,114,98],"ratio":5.66189480456812},{"$$hashKey":"object:16996","color":[150,150,148],"ratio":0.048254785266205566},{"$$hashKey":"object:16997","color":[156,164,172],"ratio":0.016084928422068524}],"size":89229,"tags":[],"url":"","width":690}