{"annotation":"","ext":"jpg","folders":["JRFVY8QUPQKXA","JRFVWA3SXEP4Q"],"height":1500,"id":"JRFVYT4ZN3ARD","isDeleted":false,"lastModified":1567270663738,"modificationTime":1548652925683,"name":"312796428","palettes":[{"color":[107,107,114],"ratio":69.89026063100137},{"color":[213,204,193],"ratio":13.671696387745772},{"color":[155,184,201],"ratio":6.104252400548696},{"color":[35,38,37],"ratio":7.841792409693644},{"color":[164,183,168],"ratio":2.4919981710105166}],"size":576666,"tags":["中国风"],"url":"","width":1000}