{"annotation":"","ext":"jpg","folders":["JRFUWIUFUQH7N","JZZMM5FHSJUV9"],"height":1390,"id":"JRFUXGOXF5SXF","isDeleted":false,"lastModified":1567271152796,"modificationTime":1548651183257,"name":"393521292","noThumbnail":true,"palettes":[{"color":[115,24,20],"ratio":85.76847612818835},{"color":[36,14,13],"ratio":12.053629823413996},{"color":[229,215,214],"ratio":1.4061478090255068},{"color":[161,155,145],"ratio":0.5951602354480052},{"color":[97,100,157],"ratio":0.17658600392413343}],"size":151973,"tags":["宝石"],"url":"","width":1100}