{"annotation":"","ext":"jpg","folders":["JZZMM5FHSJUV9"],"height":1149,"id":"K8TX2B880NQYF","isDeleted":false,"lastModified":1631589552475,"modificationTime":1586506594904,"name":"K8TX2B8TUMOOO","noThumbnail":true,"palettes":[{"color":[39,37,35],"ratio":56},{"color":[70,68,64],"ratio":13},{"color":[59,60,55],"ratio":8},{"color":[8,7,6],"ratio":7},{"color":[99,97,93],"ratio":6},{"color":[83,84,79],"ratio":3.2},{"color":[78,76,76],"ratio":3.14},{"color":[134,132,128],"ratio":1.21}],"size":258941,"tags":[],"url":"https://i.pinimg.com/originals/ce/8d/74/ce8d747e6d81dc943301b13373d26d65.jpg","width":646,"mtime":1586506595321,"btime":1628153953473}