{"annotation":"","ext":"jpg","folders":["JRFUWIUFUQH7N","JZZMM5FHSJUV9"],"height":1058,"id":"JRFUXGOYGRK7D","isDeleted":false,"lastModified":1567270920244,"modificationTime":1548651183222,"name":"607964537","palettes":[{"color":[243,240,237],"ratio":77.58335763585107},{"color":[61,41,40],"ratio":7.062311655487509},{"color":[155,82,78],"ratio":6.547098279381744},{"color":[170,144,105],"ratio":4.607757363662875},{"color":[168,158,138],"ratio":4.199475065616798}],"size":414545,"tags":[],"url":"","width":1500}