{"annotation":"","ext":"jpg","folders":["JRFVY8QUPQKXA","JRFVWA3SXEP4Q"],"height":1068,"id":"JRFVYT51NBSTR","isDeleted":false,"lastModified":1567271333945,"modificationTime":1548652925654,"name":"1249052925","palettes":[{"color":[225,236,242],"ratio":82.53275109170306},{"color":[204,220,234],"ratio":6.558305029920751},{"color":[193,215,228],"ratio":7.059679767103348},{"color":[176,204,220],"ratio":2.296619763868672},{"color":[204,228,235],"ratio":1.5526443474041727}],"size":1014261,"tags":["中国风"],"url":"","width":2520}