{"id":"K0GLEYBMRU417","name":"Super Fruit Decoration Ideas Landscapes 34 Ideas fruit","size":18321,"ext":"jpg","tags":[],"folders":[],"isDeleted":false,"url":"https://www.pinterest.com/pin/778982066777332264/","annotation":"","modificationTime":1568286710410,"noThumbnail":true,"width":306,"height":511,"lastModified":1631589855454,"palettes":[{"color":[111,113,107],"ratio":53},{"color":[69,46,34],"ratio":13},{"color":[101,77,60],"ratio":12},{"color":[159,113,85],"ratio":5},{"color":[99,64,41],"ratio":3.97},{"color":[250,245,225],"ratio":3.77},{"color":[210,155,108],"ratio":3.59},{"color":[241,208,152],"ratio":2.94}],"mtime":1568286710353,"btime":1628153950616}