{"annotation":"","ext":"jpg","folders":["JRFUWIUFUQH7N","JZZMM5FHSJUV9"],"height":579,"id":"JRFUXGOXLXKRV","isDeleted":false,"lastModified":1567271152601,"modificationTime":1548651183249,"name":"490699990","noThumbnail":true,"palettes":[{"color":[134,115,96],"ratio":77.54749568221071},{"color":[213,212,193],"ratio":9.355210132412205},{"color":[37,31,33],"ratio":4.001151410477835},{"color":[180,185,182],"ratio":4.922279792746114},{"color":[205,173,130],"ratio":4.173862982153138}],"size":171070,"tags":[],"url":"","width":600}