{"annotation":"","ext":"jpg","folders":["JZZMIIPGWW6Z3"],"height":8000,"id":"K2CR7A9M9RB8F","isDeleted":false,"modificationTime":1572408131537,"name":"围棋赛","palettes":[{"color":[14,12,15],"ratio":91.03785103785104},{"color":[206,200,200],"ratio":4.981684981684982},{"color":[96,90,96],"ratio":3.6874236874236876},{"color":[132,132,132],"ratio":0.21978021978021978},{"color":[124,118,132],"ratio":0.07326007326007326}],"size":3987645,"tags":[],"url":"https://huaban.com/pins/1932942699/","width":4500,"lastModified":1572409246006}