{"id":"JSFQP5R8531HB","name":"Adventure era 4 on Behance","size":618874,"ext":"png","tags":[],"folders":["JRCWUUXEKZCKJ"],"isDeleted":false,"url":"https://www.behance.net/gallery/22875517/Adventure-era-4","annotation":"","modificationTime":1550820859484,"noThumbnail":true,"width":600,"height":900,"lastModified":1550820935215,"palettes":[{"color":[75,182,210],"ratio":53.185185185185176},{"color":[213,235,230],"ratio":19.14814814814815},{"color":[52,44,52],"ratio":20.296296296296294},{"color":[73,104,90],"ratio":5.444444444444444},{"color":[77,105,126],"ratio":1.925925925925926}]}