{"annotation":"","ext":"jpg","folders":["JSFRT9E3QJEOX"],"height":900,"id":"JSFQPW2W6NP6Q","isDeleted":false,"lastModified":1550823851926,"modificationTime":1550820859723,"name":"Chabe Escalante  Freelance illustrat","noThumbnail":true,"palettes":[{"color":[8,8,8],"ratio":61.50617283950617},{"color":[211,211,211],"ratio":33.01234567901234},{"color":[140,140,140],"ratio":2.3703703703703702},{"color":[132,132,132],"ratio":1.9876543209876543},{"color":[124,124,124],"ratio":1.123456790123457}],"size":83596,"tags":[],"url":"https://www.artstation.com/artwork/hijab-c553a52f-540e-47f0-8865-d001b1b12e4e","width":900}