{"annotation":"","ext":"jpg","folders":["JRFUWIUFUQH7N","JZZMM5FHSJUV9"],"height":400,"id":"JRFUXGOX6A6V5","isDeleted":false,"lastModified":1631590056573,"modificationTime":1548651183266,"name":"310108863","noThumbnail":true,"palettes":[{"color":[11,12,6],"ratio":49},{"color":[104,163,28],"ratio":18},{"color":[190,188,60],"ratio":13},{"color":[55,109,40],"ratio":10},{"color":[104,104,33],"ratio":4.4},{"color":[193,118,24],"ratio":1.36},{"color":[213,220,179],"ratio":1},{"color":[183,52,21],"ratio":0.58},{"color":[40,144,19],"ratio":0.36}],"size":90606,"tags":[],"url":"","width":402,"mtime":1548251034000,"btime":1628152018767}