{"id":"JRFWDGFZWJSZP","name":"312802825","size":335891,"ext":"png","tags":[],"folders":["JRFWD8TJIPV34"],"isDeleted":false,"url":"","annotation":"","modificationTime":1548653609075,"noThumbnail":true,"width":697,"height":556,"lastModified":1548725906393,"palettes":[{"color":[34,32,32],"ratio":86.66150670794633},{"color":[187,126,75],"ratio":5.727554179566564},{"color":[113,82,66],"ratio":7.352941176470589},{"color":[138,140,138],"ratio":0.15479876160990713},{"color":[124,128,140],"ratio":0.10319917440660474}]}