{"annotation":"","ext":"jpg","folders":["JRFVY8QUPQKXA","JRFVWA3SXEP4Q"],"height":540,"id":"JRFVYT51Y5PND","isDeleted":false,"lastModified":1567271194500,"modificationTime":1548652925643,"name":"1666973938","noThumbnail":true,"palettes":[{"color":[202,163,137],"ratio":50.81018518518518},{"color":[40,41,61],"ratio":19.96527777777778},{"color":[144,46,30],"ratio":9.375},{"color":[199,98,50],"ratio":8.738425925925926},{"color":[239,236,229],"ratio":11.11111111111111}],"size":143616,"tags":["中国风"],"url":"","width":960}