{"annotation":"","ext":"jpg","folders":["JRCWUUXEKZCKJ"],"height":306,"id":"JRCVPX1C204NP","isDeleted":false,"modificationTime":1548471110938,"name":"Guillotine Games  Massive Darkness  Edouard Guiton  Eric Nouhaut","noThumbnail":true,"palettes":[{"color":[70,57,56],"ratio":20.35447244530601},{"color":[250,249,249],"ratio":73.60841872057603},{"color":[135,104,92],"ratio":1.4261977291608974},{"color":[156,159,155],"ratio":3.5031847133757963},{"color":[166,134,105],"ratio":1.1077263915812794}],"size":10996,"tags":["原画_人物"],"url":"https://www.pinterest.com/liur0010/%E5%8E%9F%E7%94%BB%E4%BA%BA%E7%89%A9/","width":236,"lastModified":1548482741035}