{"annotation":"","ext":"jpg","folders":["JZZMM5FHSJUV9"],"height":380,"id":"K0GNJ81UAY4EQ","isDeleted":false,"lastModified":1631589551754,"modificationTime":1568290271509,"name":"K0GNJ82A3FENK","noThumbnail":true,"palettes":[{"color":[228,224,218],"ratio":73},{"color":[169,156,132],"ratio":5},{"color":[192,185,165],"ratio":5},{"color":[209,201,185],"ratio":5},{"color":[184,192,189],"ratio":4.7},{"color":[118,101,75],"ratio":3.65},{"color":[160,171,163],"ratio":1.26},{"color":[178,179,180],"ratio":0.31}],"size":31230,"tags":[],"url":"https://www.pinterest.com/pin/299348706477882629/","width":400,"mtime":1568290271441,"btime":1628153950621}