{"annotation":"","ext":"jpg","folders":["JRFVX308J8ZTD"],"height":1227,"id":"JRFVXBCRP0Y7L","isDeleted":false,"modificationTime":1548652855962,"name":"1067061688","noThumbnail":true,"size":250525,"tags":["建筑"],"url":"","width":690,"lastModified":1548652890105,"palettes":[{"color":[229,226,230],"ratio":57.15129325617102},{"color":[51,36,38],"ratio":17.030825558048896},{"color":[133,78,61],"ratio":21.010983819534665},{"color":[161,123,104],"ratio":3.4250620054328573},{"color":[140,135,137],"ratio":1.3818353608125664}]}