{"annotation":"","ext":"jpg","folders":["JRFWD8TJIPV34"],"height":583,"id":"JRFWDGFZLJBOE","isDeleted":false,"modificationTime":1548653609083,"name":"252525905","noThumbnail":true,"palettes":[{"color":[21,28,52],"ratio":96.4551172098342},{"color":[50,191,182],"ratio":3.2399466361730513},{"color":[218,247,242],"ratio":0.13340956737183152},{"color":[60,118,140],"ratio":0.07623403849818944},{"color":[87,112,125],"ratio":0.0952925481227368}],"size":65113,"tags":["场景","3D"],"url":"","width":900,"lastModified":1548725891655}