{"annotation":"","ext":"jpg","folders":["JRFVX308J8ZTD"],"height":747,"id":"JRFVXBCRYSQTR","isDeleted":false,"modificationTime":1548652855966,"name":"312804546","noThumbnail":true,"palettes":[{"color":[50,42,33],"ratio":74.13984461709212},{"color":[188,175,160],"ratio":8.368479467258602},{"color":[123,105,86],"ratio":16.315205327413985},{"color":[146,149,151],"ratio":0.5993340732519422},{"color":[136,138,144],"ratio":0.5771365149833518}],"size":128452,"tags":["建筑"],"url":"","width":603,"lastModified":1548652881455}