{"annotation":"","ext":"jpg","folders":["JRFRUBBXNWOPU"],"height":626,"id":"JWLI115EYV337","isDeleted":false,"lastModified":1631589542774,"modificationTime":1559876223575,"name":"More than a million free vectors, PSD, photos and free icons. Exclusiv","noThumbnail":true,"palettes":[{"color":[227,244,234],"ratio":70},{"color":[63,114,82],"ratio":11},{"color":[192,173,69],"ratio":10},{"color":[232,160,193],"ratio":1.69},{"color":[162,109,169],"ratio":1.43},{"color":[104,83,179],"ratio":1.34},{"color":[135,82,67],"ratio":1.12},{"color":[144,179,164],"ratio":1.12},{"color":[202,189,156],"ratio":0.73},{"color":[86,206,105],"ratio":0.57},{"color":[179,219,193],"ratio":0.47}],"size":37065,"tags":[],"url":"https://www.pinterest.com/pin/364158319867789872/","width":626,"mtime":1559876223000,"btime":1628152034860}