{"annotation":"","ext":"png","folders":["JSFQNE8G10OAK"],"height":1200,"id":"JX1HUHQI8YAUQ","isDeleted":false,"lastModified":1567261756115,"modificationTime":1560843377330,"name":"Behance  Behance 作品精选","noThumbnail":true,"palettes":[{"color":[124,110,93],"ratio":65.92361111111111},{"color":[234,232,181],"ratio":17.27777777777778},{"color":[142,157,217],"ratio":6.444444444444445},{"color":[66,17,19],"ratio":7.618055555555555},{"color":[222,125,128],"ratio":2.736111111111111}],"size":1971584,"tags":[],"url":"https://www.behance.net/gallery/80479857/Illustrations-2019?tracking_source=best_of_behance_big_covers","width":1200}