{"id":"JSFQQBQEPW6JX","name":"Alchemical laboratory","size":535705,"ext":"jpg","tags":[],"folders":["JRCWUUXEKZCKJ"],"isDeleted":false,"url":"https://www.behance.net/gallery/53553357/Alchemical-laboratory","annotation":"","modificationTime":1550820859861,"noThumbnail":true,"width":845,"height":916,"lastModified":1550821079878,"palettes":[{"color":[101,94,98],"ratio":77.1993282521638},{"color":[223,141,140],"ratio":5.632347241958404},{"color":[25,46,60],"ratio":12.156052189639581},{"color":[105,212,164],"ratio":2.402790337165741},{"color":[93,126,210],"ratio":2.6094819790724713}]}