{"annotation":"","ext":"jpg","folders":["JRFVY8QUPQKXA","JRFVWA3SXEP4Q"],"height":1036,"id":"JRFVYT51EIFD7","isDeleted":false,"lastModified":1567271194412,"modificationTime":1548652925640,"name":"1666977861","palettes":[{"color":[71,110,177],"ratio":58.260150184548806},{"color":[201,201,224],"ratio":7.114674812269314},{"color":[23,44,89],"ratio":20.92401680030546},{"color":[131,155,212],"ratio":11.244749904543719},{"color":[133,195,243],"ratio":2.456408298332697}],"size":116805,"tags":["中国风"],"url":"","width":1920}