{"annotation":"","ext":"jpg","folders":["JRCWUUXEKZCKJ"],"height":354,"id":"JRCVPWKOD07QO","isDeleted":false,"modificationTime":1548471110927,"name":"really this times i feel u are verfar from me .. and i am out of ur li","noThumbnail":true,"palettes":[{"color":[194,168,166],"ratio":60.31119090365051},{"color":[70,95,137],"ratio":8.17474566128067},{"color":[115,162,203],"ratio":23.734290843806104},{"color":[124,89,84],"ratio":6.2477558348294435},{"color":[133,89,104],"ratio":1.5320167564332734}],"size":13032,"tags":["原画_人物"],"url":"https://www.pinterest.com/liur0010/%E5%8E%9F%E7%94%BB%E4%BA%BA%E7%89%A9/","width":236,"lastModified":1548482741123}