{"annotation":"","ext":"jpg","folders":["JRCWUUXEKZCKJ"],"height":900,"id":"K7FNCLMTEP5XL","isDeleted":false,"lastModified":1586763041251,"modificationTime":1583466970047,"name":"8c529f3af694084af2522c57cf8cb27f 617×900","noThumbnail":true,"palettes":[{"color":[70,63,79],"ratio":14.62272645416892},{"color":[238,231,232],"ratio":69.98019088780839},{"color":[158,91,101],"ratio":7.113272105168377},{"color":[148,174,188],"ratio":6.12281649558797},{"color":[190,149,98],"ratio":2.1609940572663424}],"size":135344,"tags":[],"url":"https://i.pinimg.com/736x/8c/52/9f/8c529f3af694084af2522c57cf8cb27f.jpg","width":617}