{"annotation":"","ext":"jpg","folders":["JRFVWA3SXEP4Q"],"height":506,"id":"JRFWDGFZ8MJRD","isDeleted":false,"modificationTime":1548653609077,"name":"252528310","noThumbnail":true,"palettes":[{"color":[231,175,134],"ratio":39,"$$hashKey":"object:9358"},{"color":[249,238,220],"ratio":24,"$$hashKey":"object:9359"},{"color":[165,41,21],"ratio":8,"$$hashKey":"object:9360"},{"color":[229,116,78],"ratio":8,"$$hashKey":"object:9361"},{"color":[241,144,86],"ratio":5,"$$hashKey":"object:9362"},{"color":[247,225,180],"ratio":4.22,"$$hashKey":"object:9363"},{"color":[155,135,114],"ratio":3.09,"$$hashKey":"object:9364"},{"color":[94,185,129],"ratio":2.28,"$$hashKey":"object:9365"},{"color":[223,112,56],"ratio":2.08,"$$hashKey":"object:9366"},{"color":[241,206,176],"ratio":1.58,"$$hashKey":"object:9367"}],"size":131363,"tags":["场景","3D"],"url":"","width":900,"lastModified":1631589935480,"mtime":1548250283000,"btime":1628152026723}