{"annotation":"","ext":"jpg","folders":["JZZMIIPGWW6Z3"],"height":736,"id":"K1J9YP5HT16UY","isDeleted":false,"lastModified":1586763268202,"modificationTime":1570625658244,"name":"Wooden bookmarks, custom bookmarks, unique bookmarks, reading lovers g","noThumbnail":true,"palettes":[{"color":[248,238,221],"ratio":80.13660697803212},{"color":[109,79,55],"ratio":7.974893852685988},{"color":[221,182,142],"ratio":11.020860254753554},{"color":[69,96,122],"ratio":0.8307181096547905},{"color":[124,124,132],"ratio":0.036920804873546244}],"size":76760,"tags":[],"url":"https://www.pinterest.com/pin/484277766181227612/","width":736}