{"annotation":"","ext":"jpg","folders":["JZZMKXZHBOGZ8"],"height":600,"id":"JZZTGK3HC15OA","isDeleted":false,"lastModified":1631590054954,"modificationTime":1567272299816,"name":"玩家网络UI图标交互网站游戏玩家网页配置文件ios android移动ux ui","noThumbnail":true,"palettes":[{"color":[226,217,228],"ratio":47},{"color":[250,226,153],"ratio":18},{"color":[112,74,103],"ratio":14},{"color":[177,139,156],"ratio":7},{"color":[193,174,192],"ratio":7},{"color":[224,164,110],"ratio":2.15},{"color":[194,99,103],"ratio":0.51}],"size":238017,"tags":[],"url":"https://dribbble.com/shots/3815146-Gamer-network-UI","width":800,"mtime":1567272299754,"btime":1628153950314}