{"annotation":"","ext":"jpg","folders":["JRFVY8QUPQKXA","JRFVWA3SXEP4Q"],"height":915,"id":"JRFVYT4ZIYTMK","isDeleted":false,"lastModified":1567270663732,"modificationTime":1548652925682,"name":"312796691","palettes":[{"color":[70,87,107],"ratio":72.1403376165281},{"color":[201,195,194],"ratio":8.484504913076343},{"color":[140,142,149],"ratio":17.006802721088434},{"color":[153,163,189],"ratio":2.015621063240111},{"color":[153,188,194],"ratio":0.3527336860670194}],"size":840017,"tags":["中国风"],"url":"","width":1680}