{"id":"JSFQPW1GY51OD","name":"一般角色 欧美 现代 Childhood Heroes on Behan","size":914164,"ext":"png","tags":[],"folders":["JRCWUUXEKZCKJ"],"isDeleted":false,"url":"https://www.behance.net/gallery/28914331/Childhood-Heroes","annotation":"","modificationTime":1550820859721,"height":2428,"width":661,"lastModified":1550821025840,"palettes":[{"color":[250,247,245],"ratio":76.86204965465745},{"color":[64,43,55],"ratio":8.017547134590256},{"color":[192,76,81],"ratio":8.250886690311741},{"color":[235,180,72],"ratio":3.3694231846182565},{"color":[154,197,179],"ratio":3.5000933358222888}]}