{"annotation":"","ext":"jpg","folders":["JRFWL4TIXLNSZ"],"height":891,"id":"K8SJO40B59C8V","isDeleted":false,"lastModified":1586762973746,"modificationTime":1586423631179,"name":"Niice. A search engine with taste.","noThumbnail":true,"palettes":[{"color":[221,80,81],"ratio":66.96595585484474},{"color":[54,38,37],"ratio":6.921062476618032},{"color":[238,226,165],"ratio":14.515525626636737},{"color":[202,144,117],"ratio":11.410400299289188},{"color":[243,149,175],"ratio":0.18705574261129815}],"size":76857,"tags":[],"url":"https://niice.co/?search=jukebox","width":600}