{"annotation":"","ext":"jpg","folders":["JRFVY8QUPQKXA","JRFVWA3SXEP4Q"],"height":900,"id":"JRFVYT4ZV690E","isDeleted":false,"lastModified":1567270663708,"modificationTime":1548652925681,"name":"312797166","palettes":[{"color":[68,63,101],"ratio":80.44124371284866},{"color":[219,198,162],"ratio":7.453132144490169},{"color":[133,126,141],"ratio":9.024919981710106},{"color":[172,144,145],"ratio":2.8177869227251944},{"color":[122,113,189],"ratio":0.2629172382258802}],"size":683299,"tags":["中国风"],"url":"","width":1500}