{"id":"JRFRNCDXIQVPC","name":"452892483","size":197085,"ext":"jpg","tags":[],"folders":["JRFQUSM76F7ZE"],"isDeleted":false,"url":"","annotation":"","modificationTime":1548645672309,"noThumbnail":true,"width":736,"height":1140,"lastModified":1548645672530,"palettes":[{"color":[224,224,224],"ratio":80.15731140507687},{"color":[67,67,67],"ratio":10.165653676558218},{"color":[140,140,140],"ratio":6.876415206769157},{"color":[108,108,108],"ratio":1.5850315814563223},{"color":[116,116,116],"ratio":1.2155881301394351}]}