{"annotation":"","ext":"jpg","folders":["JRFRUBBXNWOPU"],"height":300,"id":"K8ZIFG36LOP1V","isDeleted":false,"lastModified":1631589540813,"modificationTime":1586844810546,"name":"Vip icon","noThumbnail":true,"palettes":[{"color":[147,211,211],"ratio":86},{"color":[239,173,67],"ratio":8},{"color":[247,204,135],"ratio":3.44},{"color":[187,73,36],"ratio":0.92},{"color":[143,180,165],"ratio":0.36}],"size":6291,"tags":[],"url":"https://dribbble.com/shots/1824126-Vip-icon","width":400,"mtime":1586844810710,"btime":1628153953762}